json_duplicate_keys/__init__.py
json_duplicate_keys-2025.9.30.dist-info/LICENSE
json_duplicate_keys-2025.9.30.dist-info/METADATA
json_duplicate_keys-2025.9.30.dist-info/WHEEL
json_duplicate_keys-2025.9.30.dist-info/top_level.txt
json_duplicate_keys-2025.9.30.dist-info/RECORD
