Metadata-Version: 2.1
Name: json-duplicate-keys
Version: 2025.9.30
Summary: Flatten/ Unflatten and Load(s)/ Dump(s) JSON File/ Object with Duplicate Keys
Author-email: TP Cyber Security <tpcybersec2023@gmail.com>
License: MIT
Project-URL: Homepage, https://github.com/TPCyberSec/json-duplicate-keys
Keywords: TPCyberSec,json,duplicate keys,json duplicate keys,flatten,unflatten
Classifier: Programming Language :: Python :: 3
Classifier: Programming Language :: Python :: Implementation :: Jython
License-File: LICENSE
